foliumYandexPracticum/__init__.py
foliumYandexPracticum/_version.py
foliumYandexPracticum/elements.py
foliumYandexPracticum/features.py
foliumYandexPracticum/folium.py
foliumYandexPracticum/map.py
foliumYandexPracticum/raster_layers.py
foliumYandexPracticum/utilities.py
foliumYandexPracticum/vector_layers.py
foliumYandexPracticum/plugins/__init__.py
foliumYandexPracticum/plugins/antpath.py
foliumYandexPracticum/plugins/beautify_icon.py
foliumYandexPracticum/plugins/boat_marker.py
foliumYandexPracticum/plugins/draw.py
foliumYandexPracticum/plugins/dual_map.py
foliumYandexPracticum/plugins/fast_marker_cluster.py
foliumYandexPracticum/plugins/feature_group_sub_group.py
foliumYandexPracticum/plugins/float_image.py
foliumYandexPracticum/plugins/fullscreen.py
foliumYandexPracticum/plugins/geocoder.py
foliumYandexPracticum/plugins/heat_map.py
foliumYandexPracticum/plugins/heat_map_withtime.py
foliumYandexPracticum/plugins/locate_control.py
foliumYandexPracticum/plugins/marker_cluster.py
foliumYandexPracticum/plugins/measure_control.py
foliumYandexPracticum/plugins/minimap.py
foliumYandexPracticum/plugins/mouse_position.py
foliumYandexPracticum/plugins/pattern.py
foliumYandexPracticum/plugins/polyline_offset.py
foliumYandexPracticum/plugins/polyline_text_path.py
foliumYandexPracticum/plugins/scroll_zoom_toggler.py
foliumYandexPracticum/plugins/search.py
foliumYandexPracticum/plugins/semicircle.py
foliumYandexPracticum/plugins/terminator.py
foliumYandexPracticum/plugins/time_slider_choropleth.py
foliumYandexPracticum/plugins/timestamped_geo_json.py
foliumYandexPracticum/plugins/timestamped_wmstilelayer.py
foliumYandexPracticum/templates/fit_bounds.js
foliumYandexPracticum/templates/leaflet_heat.min.js
foliumYandexPracticum/templates/pa7_hm.min.js
foliumYandexPracticum/templates/pa7_leaflet_hm.min.js
foliumYandexPracticum/templates/tiles/cartodbdark_matter/attr.txt
foliumYandexPracticum/templates/tiles/cartodbdark_matter/tiles.txt
foliumYandexPracticum-3.0.0.dist-info/LICENSE.txt
foliumYandexPracticum-3.0.0.dist-info/METADATA
foliumYandexPracticum-3.0.0.dist-info/WHEEL
foliumYandexPracticum-3.0.0.dist-info/top_level.txt
foliumYandexPracticum-3.0.0.dist-info/RECORD
