Metadata-Version: 2.1
Name: foliumYandexPracticum
Version: 3.0.0
Summary: Folium library with local version of map
Home-page: https://python-visualization.github.io/
Author: data.practicum
Author-email: data.practicum@yandex.ru
License: UNKNOWN
Project-URL: Documentation, https://python-visualization.github.io/folium/latest/user_guide.html
Keywords: example python
Platform: UNKNOWN
Classifier: Programming Language :: Python :: 3.11
Classifier: License :: OSI Approved :: MIT License
Classifier: Operating System :: OS Independent
Requires-Python: >=3.7
License-File: LICENSE.txt
Requires-Dist: branca
Requires-Dist: Jinja2
Requires-Dist: numpy
Requires-Dist: requests
